WereSync-1.1.5.data/data/share/icons/hicolor/scalable/apps/weresync.svg
weresync/__init__.py
weresync/exception.py
weresync/utils.py
weresync/daemon/__init__.py
weresync/daemon/copier.py
weresync/daemon/daemon.py
weresync/daemon/device.py
weresync/interface/__init__.py
weresync/interface/cli.py
weresync/interface/dbus_client.py
weresync/interface/gui.py
weresync/plugins/__init__.py
weresync/plugins/weresync_grub2.py
weresync/plugins/weresync_syslinux.py
weresync/plugins/weresync_uuid_copy.py
weresync/resources/__init__.py
weresync/resources/weresync-dbus.conf
weresync/resources/weresync-gui.desktop
weresync/resources/weresync.service
weresync/resources/weresync.svg
weresync/resources/locale/en/LC_MESSAGES/weresync.mo
WereSync-1.1.5.dist-info/LICENSE.txt
WereSync-1.1.5.dist-info/METADATA
WereSync-1.1.5.dist-info/WHEEL
WereSync-1.1.5.dist-info/entry_points.txt
WereSync-1.1.5.dist-info/top_level.txt
WereSync-1.1.5.dist-info/RECORD
