Metadata-Version: 2.1
Name: WereSync
Version: 1.1.5
Summary: Incrementally clones Linux drives
Home-page: https://github.com/DonyorM/weresync
Author: Daniel Manila
Author-email: dmv@springwater7.org
License: Apache 2.0
Keywords: clone,linux,backup,smaller drive
Platform: UNKNOWN
Requires-Dist: parse (==1.6.6)
Requires-Dist: yapsy (==1.11.223)
Requires-Dist: pydbus (==0.6.0)
